py_send_m365/__init__.py
py_send_m365/m365_mail.py
py_send_m365-0.3.3.dist-info/LICENSE
py_send_m365-0.3.3.dist-info/METADATA
py_send_m365-0.3.3.dist-info/WHEEL
py_send_m365-0.3.3.dist-info/top_level.txt
py_send_m365-0.3.3.dist-info/RECORD
