Metadata-Version: 2.2
Name: py_send_m365
Version: 0.3.3
Summary: A simple library to send email from an existing M365 account in Python
Author-email: Linus Pauls <hadoken79@protonmail.com>
License: MIT
Project-URL: Homepage, https://github.com/hadoken79/py_send_m365
Project-URL: Bug Tracker, https://github.com/hadoken79/py_send_m365/issues
Keywords: email,M365,Microsoft,SMTP,Python
Classifier: Programming Language :: Python :: 3
Classifier: License :: OSI Approved :: MIT License
Classifier: Operating System :: OS Independent
Requires-Python: >=3.6
License-File: LICENSE
